topsis_manraj_102303221/__init__.py
topsis_manraj_102303221/topsis.py
topsis_manraj_102303221-0.0.1.dist-info/licenses/LICENCE
topsis_manraj_102303221-0.0.1.dist-info/METADATA
topsis_manraj_102303221-0.0.1.dist-info/WHEEL
topsis_manraj_102303221-0.0.1.dist-info/entry_points.txt
topsis_manraj_102303221-0.0.1.dist-info/top_level.txt
topsis_manraj_102303221-0.0.1.dist-info/RECORD
