Metadata-Version: 2.4
Name: topsis-manraj-102303221
Version: 0.0.1
Summary: TOPSIS implementation using Python
Author: Manraj Khehra
Author-email: your_email@gmail.com
Classifier: Programming Language :: Python :: 3
Classifier: License :: OSI Approved :: MIT License
Classifier: Operating System :: OS Independent
License-File: LICENCE
Requires-Dist: numpy
Requires-Dist: pandas
Dynamic: author
Dynamic: author-email
Dynamic: classifier
Dynamic: description
Dynamic: description-content-type
Dynamic: license-file
Dynamic: requires-dist
Dynamic: summary
